seco.py
SeCo-1.1.0.dist-info/DESCRIPTION.rst
SeCo-1.1.0.dist-info/METADATA
SeCo-1.1.0.dist-info/RECORD
SeCo-1.1.0.dist-info/WHEEL
SeCo-1.1.0.dist-info/metadata.json
SeCo-1.1.0.dist-info/top_level.txt
