Metadata-Version: 2.0
Name: SeCo
Version: 1.1.0
Summary: Python data serialization and compression made easy.
Home-page: https://www.github.com/copyrighthero/SeCo
Author: Hansheng Zhao
Author-email: copyrighthero@gmail.com
License: BSD-2-Clause + MIT
Download-URL: https://www.github.com/copyrighthero/SeCo
Project-URL: Source, https://www.github.com/copyrighthero/SeCo
Keywords: Data Serialization Compression Library
Platform: UNKNOWN
Classifier: Development Status :: 5 - Production/Stable
Classifier: Intended Audience :: Developers
Classifier: Intended Audience :: End Users/Desktop
Classifier: Intended Audience :: Information Technology
Classifier: Intended Audience :: Science/Research
Classifier: Intended Audience :: System Administrators
Classifier: License :: OSI Approved :: BSD License
Classifier: License :: OSI Approved :: MIT License
Classifier: Natural Language :: English
Classifier: Operating System :: OS Independent
Classifier: Programming Language :: Python :: 2
Classifier: Programming Language :: Python :: 3
Classifier: Topic :: Communications
Classifier: Topic :: Database
Classifier: Topic :: Internet
Classifier: Topic :: Software Development
Classifier: Topic :: System
Classifier: Topic :: Utilities
Requires-Dist: simplejson
Requires-Dist: msgpack-python
